LICENSE
MANIFEST.in
README
bootstrap.py
buildout.cfg
setup.py
build-tools/README
build-tools/build.sh
build-tools/django-settings.py.in
build-tools/SPECS/transifex.spec.in
transifex/__init__.py
transifex/manage.py
transifex/search_indexes.py
transifex/settings.py
transifex/urls.py
transifex/views.py
transifex.egg-info/PKG-INFO
transifex.egg-info/SOURCES.txt
transifex.egg-info/dependency_links.txt
transifex.egg-info/not-zip-safe
transifex.egg-info/requires.txt
transifex.egg-info/top_level.txt
transifex/actionlog/__init__.py
transifex/actionlog/admin.py
transifex/actionlog/api.py
transifex/actionlog/filters.py
transifex/actionlog/models.py
transifex/actionlog/migrations/0001_initial.py
transifex/actionlog/migrations/__init__.py
transifex/actionlog/templates/object_action_list.html
transifex/actionlog/templatetags/__init__.py
transifex/actionlog/templatetags/tx_action_log.py
transifex/actionlog/tests/__init__.py
transifex/actionlog/tests/api.py
transifex/addons/__init__.py
transifex/addons/autofetch/__init__.py
transifex/addons/autofetch/admin.py
transifex/addons/autofetch/forms.py
transifex/addons/autofetch/models.py
transifex/addons/autofetch/tests.py
transifex/addons/autofetch/urls.py
transifex/addons/autofetch/views.py
transifex/addons/autofetch/management/__init__.py
transifex/addons/autofetch/management/commands/__init__.py
transifex/addons/autofetch/management/commands/txfetch.py
transifex/addons/autofetch/migrations/0001_initial.py
transifex/addons/autofetch/migrations/0002_convert_fk_to_1on1.py
transifex/addons/autofetch/migrations/__init__.py
transifex/addons/charts/__init__.py
transifex/addons/charts/gviz_api.py
transifex/addons/charts/models.py
transifex/addons/charts/tests.py
transifex/addons/charts/urls.py
transifex/addons/charts/views.py
transifex/addons/charts/templates/resource_chart.html
transifex/addons/charts/templates/resource_chart_js.html
transifex/addons/charts/templates/charts/widget_snippet.html
transifex/addons/copyright/__init__.py
transifex/addons/copyright/handlers.py
transifex/addons/copyright/models.py
transifex/addons/copyright/tests.py
transifex/addons/copyright/migrations/0001_initial.py
