Metadata-Version: 1.0
Name: transifex
Version: 1.2.0
Summary: The software behind Transifex.net, the open service to collaboratively translate software, documentation and websites.
Home-page: http://transifex.org/
Author: The Transifex community and the staff of Indifex
Author-email: transifex-devel@googlegroups.com
License: GPLv2
Keywords: django.app,translation localization internationalization vcs
Platform: UNKNOWN
Classifier: Development Status :: 5 - Production/Stable
Classifier: Environment :: Web Environment
Classifier: Framework :: Django
Classifier: Intended Audience :: Developers
Classifier: License :: OSI Approved :: GNU General Public License (GPL)
Classifier: Operating System :: OS Independent
Classifier: Programming Language :: Python
Classifier: Topic :: Software Development :: Localization
Classifier: Topic :: Software Development :: Internationalization
Classifier: Natural Language :: English
Classifier: Natural Language :: Polish
